cinder/app/__init__.py
cinder/app/server.py
cinder/ml_analysis/__init__.py
cinder/ml_analysis/code_generator.py
cinder/ml_analysis/improvement_advisor.py
cinder/model_interface/__init__.py
cinder/model_interface/connector.py
cinder_ml_dashboard-0.1.0.dist-info/METADATA
cinder_ml_dashboard-0.1.0.dist-info/WHEEL
cinder_ml_dashboard-0.1.0.dist-info/entry_points.txt
cinder_ml_dashboard-0.1.0.dist-info/licenses/LICENSE.txt
cinder_ml_dashboard-0.1.0.dist-info/RECORD
