Metadata-Version: 2.4
Name: cinder-ml-dashboard
Version: 0.1.0
Summary: A machine learning model analysis dashboard with AI assistant
Project-URL: Homepage, https://github.com/RahulThennarasu/cinder
Project-URL: Bug Tracker, https://github.com/RahulThennarasu/cinder/issues
Author-email: Rahul Thennarasu <rahulthennarasu07@gmail.com>
License-File: LICENSE.txt
Classifier: License :: OSI Approved :: MIT License
Classifier: Operating System :: OS Independent
Classifier: Programming Language :: Python :: 3
Requires-Python: >=3.8
Requires-Dist: fastapi>=0.95.0
Requires-Dist: matplotlib>=3.5.0
Requires-Dist: numpy>=1.20.0
Requires-Dist: pandas>=1.3.0
Requires-Dist: python-dotenv>=1.0.0
Requires-Dist: scikit-learn>=1.0.0
Requires-Dist: uvicorn>=0.15.0
Provides-Extra: all
Requires-Dist: google-generativeai>=0.1.0; extra == 'all'
Requires-Dist: tensorflow>=2.8.0; extra == 'all'
Requires-Dist: torch>=1.12.0; extra == 'all'
Provides-Extra: pytorch
Requires-Dist: torch>=1.12.0; extra == 'pytorch'
Provides-Extra: tensorflow
Requires-Dist: tensorflow>=2.8.0; extra == 'tensorflow'
